{
  "$schema": "https://design-tokens.github.io/community-group/format/",
  "$description": "Loop-Vesper Design Tokens - Platform-agnostic token definitions",
  "$metadata": {
    "source": "Loop-Vesper (src/app/globals.css)",
    "lastUpdated": "2026-02-03",
    "version": "1.0.0"
  },
  "color": {
    "$description": "Color tokens using HSL values for flexible alpha manipulation",
    "light": {
      "$description": "Light mode color palette - warm, minimal aesthetic",
      "background": {
        "$value": "hsl(35 20% 97%)",
        "$description": "Warm cream - main app background",
        "hsl": "35 20% 97%",
        "hex": "#FAF8F5"
      },
      "foreground": {
        "$value": "hsl(0 0% 10%)",
        "$description": "Deep charcoal - primary text",
        "hsl": "0 0% 10%",
        "hex": "#1A1A1A"
      },
      "card": {
        "$value": "hsl(0 0% 100%)",
        "$description": "Pure white - card surfaces",
        "hsl": "0 0% 100%",
        "hex": "#FFFFFF"
      },
      "cardForeground": {
        "$value": "hsl(0 0% 10%)",
        "hsl": "0 0% 10%",
        "hex": "#1A1A1A"
      },
      "popover": {
        "$value": "hsl(0 0% 100%)",
        "hsl": "0 0% 100%",
        "hex": "#FFFFFF"
      },
      "popoverForeground": {
        "$value": "hsl(0 0% 10%)",
        "hsl": "0 0% 10%",
        "hex": "#1A1A1A"
      },
      "primary": {
        "$value": "hsl(263 66% 44%)",
        "$description": "Purple - primary brand accent",
        "hsl": "263 66% 44%",
        "hex": "#6B26B8"
      },
      "primaryForeground": {
        "$value": "hsl(0 0% 100%)",
        "hsl": "0 0% 100%",
        "hex": "#FFFFFF"
      },
      "secondary": {
        "$value": "hsl(35 25% 92%)",
        "$description": "Soft warm gray - secondary surfaces",
        "hsl": "35 25% 92%",
        "hex": "#F2EDE6"
      },
      "secondaryForeground": {
        "$value": "hsl(0 0% 10%)",
        "hsl": "0 0% 10%",
        "hex": "#1A1A1A"
      },
      "muted": {
        "$value": "hsl(35 15% 90%)",
        "$description": "Muted warm gray - subtle backgrounds",
        "hsl": "35 15% 90%",
        "hex": "#EBE7E2"
      },
      "mutedForeground": {
        "$value": "hsl(0 0% 45%)",
        "$description": "De-emphasized text",
        "hsl": "0 0% 45%",
        "hex": "#737373"
      },
      "accent": {
        "$value": "hsl(263 66% 44%)",
        "$description": "Purple - interactive accent",
        "hsl": "263 66% 44%",
        "hex": "#6B26B8"
      },
      "accentForeground": {
        "$value": "hsl(0 0% 100%)",
        "hsl": "0 0% 100%",
        "hex": "#FFFFFF"
      },
      "destructive": {
        "$value": "hsl(0 72% 51%)",
        "$description": "Red - errors, dangerous actions",
        "hsl": "0 72% 51%",
        "hex": "#DC2626"
      },
      "destructiveForeground": {
        "$value": "hsl(0 0% 100%)",
        "hsl": "0 0% 100%",
        "hex": "#FFFFFF"
      },
      "border": {
        "$value": "hsl(35 10% 88%)",
        "$description": "Soft border color",
        "hsl": "35 10% 88%",
        "hex": "#E5E2DD"
      },
      "input": {
        "$value": "hsl(35 10% 88%)",
        "$description": "Input field borders",
        "hsl": "35 10% 88%",
        "hex": "#E5E2DD"
      },
      "ring": {
        "$value": "hsl(263 66% 44%)",
        "$description": "Focus ring color",
        "hsl": "263 66% 44%",
        "hex": "#6B26B8"
      }
    },
    "dark": {
      "$description": "Dark mode color palette - sleek, modern aesthetic",
      "background": {
        "$value": "hsl(0 0% 8%)",
        "$description": "Deep dark background",
        "hsl": "0 0% 8%",
        "hex": "#141414"
      },
      "foreground": {
        "$value": "hsl(0 0% 98%)",
        "$description": "Almost white text",
        "hsl": "0 0% 98%",
        "hex": "#FAFAFA"
      },
      "card": {
        "$value": "hsl(0 0% 12%)",
        "$description": "Slightly elevated card surface",
        "hsl": "0 0% 12%",
        "hex": "#1F1F1F"
      },
      "cardForeground": {
        "$value": "hsl(0 0% 98%)",
        "hsl": "0 0% 98%",
        "hex": "#FAFAFA"
      },
      "popover": {
        "$value": "hsl(0 0% 12%)",
        "hsl": "0 0% 12%",
        "hex": "#1F1F1F"
      },
      "popoverForeground": {
        "$value": "hsl(0 0% 98%)",
        "hsl": "0 0% 98%",
        "hex": "#FAFAFA"
      },
      "primary": {
        "$value": "hsl(131 100% 85%)",
        "$description": "Mint green - primary brand accent",
        "hsl": "131 100% 85%",
        "hex": "#B3FFD1"
      },
      "primaryForeground": {
        "$value": "hsl(0 0% 10%)",
        "$description": "Dark text on mint surfaces",
        "hsl": "0 0% 10%",
        "hex": "#1A1A1A"
      },
      "secondary": {
        "$value": "hsl(0 0% 16%)",
        "$description": "Dark gray secondary surface",
        "hsl": "0 0% 16%",
        "hex": "#292929"
      },
      "secondaryForeground": {
        "$value": "hsl(0 0% 98%)",
        "hsl": "0 0% 98%",
        "hex": "#FAFAFA"
      },
      "muted": {
        "$value": "hsl(0 0% 18%)",
        "$description": "Muted dark surface",
        "hsl": "0 0% 18%",
        "hex": "#2E2E2E"
      },
      "mutedForeground": {
        "$value": "hsl(0 0% 60%)",
        "$description": "De-emphasized text",
        "hsl": "0 0% 60%",
        "hex": "#999999"
      },
      "accent": {
        "$value": "hsl(131 100% 85%)",
        "$description": "Mint green - interactive accent",
        "hsl": "131 100% 85%",
        "hex": "#B3FFD1"
      },
      "accentForeground": {
        "$value": "hsl(0 0% 10%)",
        "hsl": "0 0% 10%",
        "hex": "#1A1A1A"
      },
      "destructive": {
        "$value": "hsl(0 72% 55%)",
        "$description": "Slightly brighter red for dark mode",
        "hsl": "0 72% 55%",
        "hex": "#E53E3E"
      },
      "destructiveForeground": {
        "$value": "hsl(0 0% 100%)",
        "hsl": "0 0% 100%",
        "hex": "#FFFFFF"
      },
      "border": {
        "$value": "hsl(0 0% 20%)",
        "$description": "Subtle dark border",
        "hsl": "0 0% 20%",
        "hex": "#333333"
      },
      "input": {
        "$value": "hsl(0 0% 20%)",
        "hsl": "0 0% 20%",
        "hex": "#333333"
      },
      "ring": {
        "$value": "hsl(131 100% 85%)",
        "$description": "Mint focus ring",
        "hsl": "131 100% 85%",
        "hex": "#B3FFD1"
      }
    }
  },
  "radius": {
    "$description": "Border radius tokens for consistent rounded corners",
    "base": {
      "$value": "0.75rem",
      "$description": "Base border radius (12px)"
    },
    "lg": {
      "$value": "0.75rem",
      "$description": "Large radius, equals base"
    },
    "md": {
      "$value": "calc(0.75rem - 2px)",
      "$description": "Medium radius (~10px)"
    },
    "sm": {
      "$value": "calc(0.75rem - 4px)",
      "$description": "Small radius (~8px)"
    },
    "full": {
      "$value": "9999px",
      "$description": "Fully rounded (pills, circles)"
    }
  },
  "typography": {
    "$description": "Typography tokens for consistent text styling",
    "fontFamily": {
      "sans": {
        "$value": "'Space Grotesk', ui-sans-serif, system-ui, -apple-system, BlinkMacSystemFont, 'Segoe UI', sans-serif",
        "$description": "Primary sans-serif font stack"
      },
      "display": {
        "$value": "'Avantt', 'Space Grotesk', ui-sans-serif, system-ui, sans-serif",
        "$description": "Display/heading font (bold weight only)"
      }
    },
    "fontWeight": {
      "normal": { "$value": "400" },
      "medium": { "$value": "500" },
      "semibold": { "$value": "600" },
      "bold": { "$value": "700" }
    },
    "lineHeight": {
      "tight": { "$value": "1.25" },
      "normal": { "$value": "1.5" },
      "relaxed": { "$value": "1.75" }
    }
  },
  "spacing": {
    "$description": "Spacing scale based on 4px base unit",
    "0": { "$value": "0" },
    "1": { "$value": "0.25rem", "$description": "4px" },
    "2": { "$value": "0.5rem", "$description": "8px" },
    "3": { "$value": "0.75rem", "$description": "12px" },
    "4": { "$value": "1rem", "$description": "16px" },
    "5": { "$value": "1.25rem", "$description": "20px" },
    "6": { "$value": "1.5rem", "$description": "24px" },
    "8": { "$value": "2rem", "$description": "32px" },
    "10": { "$value": "2.5rem", "$description": "40px" },
    "12": { "$value": "3rem", "$description": "48px" },
    "16": { "$value": "4rem", "$description": "64px" },
    "20": { "$value": "5rem", "$description": "80px" },
    "24": { "$value": "6rem", "$description": "96px" }
  },
  "shadow": {
    "$description": "Soft, modern shadows with low opacity",
    "sm": {
      "$value": "0 1px 3px 0 rgba(0, 0, 0, 0.04), 0 1px 2px 0 rgba(0, 0, 0, 0.02)",
      "$description": "Small shadow for subtle elevation"
    },
    "default": {
      "$value": "0 4px 6px -1px rgba(0, 0, 0, 0.06), 0 2px 4px -1px rgba(0, 0, 0, 0.03)",
      "$description": "Default shadow for cards and elevated surfaces"
    },
    "lg": {
      "$value": "0 10px 15px -3px rgba(0, 0, 0, 0.08), 0 4px 6px -2px rgba(0, 0, 0, 0.04)",
      "$description": "Large shadow for modals and overlays"
    }
  },
  "motion": {
    "$description": "Animation and transition tokens",
    "duration": {
      "instant": { "$value": "0ms" },
      "fast": { "$value": "100ms" },
      "normal": { "$value": "200ms", "$description": "Default transition duration" },
      "slow": { "$value": "400ms" },
      "slower": { "$value": "1000ms" }
    },
    "easing": {
      "default": { "$value": "ease" },
      "in": { "$value": "ease-in" },
      "out": { "$value": "ease-out" },
      "inOut": { "$value": "ease-in-out" }
    }
  },
  "layout": {
    "$description": "Layout tokens for dock/prompt bar system",
    "dock": {
      "bottom": {
        "$value": "1.5rem",
        "$description": "Distance from viewport bottom (24px)"
      },
      "gap": {
        "$value": "1rem",
        "$description": "Gap between dock elements (16px)"
      },
      "leftGutter": {
        "base": { "$value": "6rem", "$description": "96px" },
        "xl": { "$value": "12rem", "$description": "192px at 1280px+" }
      },
      "panelWidth": {
        "base": { "$value": "320px" },
        "lg": { "$value": "360px", "$description": "at 1024px+" },
        "xl": { "$value": "400px", "$description": "at 1280px+" },
        "2xl": { "$value": "440px", "$description": "at 1536px+" },
        "3xl": { "$value": "500px", "$description": "at 1800px+" }
      },
      "promptMaxWidth": {
        "base": { "$value": "42rem", "$description": "672px" },
        "lg": { "$value": "48rem", "$description": "768px at 1024px+" },
        "xl": { "$value": "56rem", "$description": "896px at 1280px+" },
        "2xl": { "$value": "64rem", "$description": "1024px at 1536px+" },
        "3xl": { "$value": "72rem", "$description": "1152px at 1800px+" }
      },
      "promptMaxWidthMulti": {
        "base": { "$value": "48rem", "$description": "768px for multi-image models" },
        "lg": { "$value": "56rem", "$description": "896px at 1024px+" },
        "xl": { "$value": "64rem", "$description": "1024px at 1280px+" },
        "2xl": { "$value": "72rem", "$description": "1152px at 1536px+" },
        "3xl": { "$value": "80rem", "$description": "1280px at 1800px+" }
      }
    },
    "breakpoints": {
      "sm": { "$value": "640px" },
      "md": { "$value": "768px" },
      "lg": { "$value": "1024px" },
      "xl": { "$value": "1280px" },
      "2xl": { "$value": "1536px" },
      "3xl": { "$value": "1800px" }
    },
    "container": {
      "maxWidth": { "$value": "1400px" },
      "padding": { "$value": "2rem" }
    }
  },
  "zIndex": {
    "$description": "Z-index scale for layering",
    "dropdown": { "$value": "50" },
    "sticky": { "$value": "100" },
    "modal": { "$value": "200" },
    "popover": { "$value": "300" },
    "tooltip": { "$value": "400" },
    "toast": { "$value": "500" }
  }
}
